MANIFEST.in
README.md
setup.py
rbbz/__init__.py
rbbz/auth.py
rbbz/bugzilla.py
rbbz/diffs.py
rbbz/errors.py
rbbz/extension.py
rbbz/forms.py
rbbz/middleware.py
rbbz/models.py
rbbz/resources.py
rbbz/transports.py
rbbz.egg-info/PKG-INFO
rbbz.egg-info/SOURCES.txt
rbbz.egg-info/dependency_links.txt
rbbz.egg-info/entry_points.txt
rbbz.egg-info/top_level.txt