Metadata-Version: 1.0
Name: rbbz
Version: 0.2.8
Summary: Review Board extension for Bugzilla support
Home-page: https://github.com/mozilla/rbbz
Author: Mark Cote
Author-email: mcote@mozilla.com
License: MPL 2.0
Platform: UNKNOWN
